[{"id":"8bf70583.ef9238","type":"subflow","name":"HUE Button Event Filter","info":"","category":"","in":[{"x":220,"y":440,"wires":[{"id":"31eb8fe1.8937e"}]}],"out":[{"x":1060,"y":180,"wires":[{"id":"edeaaab6.47f6b8","port":0}]},{"x":1060,"y":380,"wires":[{"id":"2877a094.1bfd2","port":0}]},{"x":1060,"y":540,"wires":[{"id":"247f63db.3b6bec","port":0}]},{"x":1060,"y":700,"wires":[{"id":"a1e66691.7ceb58","port":0}]}],"env":[],"color":"#DDAA99"},{"id":"3d0704f5.dd228c","type":"rbe","z":"8bf70583.ef9238","name":"","func":"rbe","gap":"","start":"","inout":"out","septopics":true,"property":"payload","x":810,"y":180,"wires":[["edeaaab6.47f6b8"]]},{"id":"edeaaab6.47f6b8","type":"switch","z":"8bf70583.ef9238","name":"","property":"payload","propertyType":"msg","rules":[{"t":"true"}],"checkall":"true","repair":false,"outputs":1,"x":930,"y":180,"wires":[[]]},{"id":"9708f490.335c08","type":"change","z":"8bf70583.ef9238","name":"false","rules":[{"t":"set","p":"payload","pt":"msg","to":"false","tot":"bool"}],"action":"","property":"","from":"","to":"","reg":false,"x":810,"y":140,"wires":[["3e3b648a.73d45c"]]},{"id":"3e3b648a.73d45c","type":"delay","z":"8bf70583.ef9238","name":"2s","pauseType":"delay","timeout":"2","timeoutUnits":"seconds","rate":"1","nbRateUnits":"1","rateUnits":"second","randomFirst":"1","randomLast":"5","randomUnits":"seconds","drop":false,"x":930,"y":140,"wires":[["3d0704f5.dd228c"]]},{"id":"19dcf962.c49ee7","type":"change","z":"8bf70583.ef9238","name":"true","rules":[{"t":"set","p":"payload","pt":"msg","to":"true","tot":"bool"}],"action":"","property":"","from":"","to":"","reg":false,"x":810,"y":220,"wires":[["3d0704f5.dd228c"]]},{"id":"e26ac54.741de38","type":"delay","z":"8bf70583.ef9238","name":"2s","pauseType":"delay","timeout":"2","timeoutUnits":"seconds","rate":"1","nbRateUnits":"1","rateUnits":"second","randomFirst":"1","randomLast":"5","randomUnits":"seconds","drop":false,"x":930,"y":660,"wires":[["f42b27c7.aec6e8"]]},{"id":"f42b27c7.aec6e8","type":"rbe","z":"8bf70583.ef9238","name":"","func":"rbe","gap":"","start":"","inout":"out","septopics":true,"property":"payload","x":810,"y":700,"wires":[["a1e66691.7ceb58"]]},{"id":"893962e6.dfef3","type":"change","z":"8bf70583.ef9238","name":"false","rules":[{"t":"set","p":"payload","pt":"msg","to":"false","tot":"bool"}],"action":"","property":"","from":"","to":"","reg":false,"x":810,"y":660,"wires":[["e26ac54.741de38"]]},{"id":"6050183b.247748","type":"change","z":"8bf70583.ef9238","name":"true","rules":[{"t":"set","p":"payload","pt":"msg","to":"true","tot":"bool"}],"action":"","property":"","from":"","to":"","reg":false,"x":810,"y":740,"wires":[["f42b27c7.aec6e8"]]},{"id":"a1e66691.7ceb58","type":"switch","z":"8bf70583.ef9238","name":"","property":"payload","propertyType":"msg","rules":[{"t":"true"}],"checkall":"true","repair":false,"outputs":1,"x":930,"y":700,"wires":[[]]},{"id":"31eb8fe1.8937e","type":"switch","z":"8bf70583.ef9238","name":"payload.data.0.button.last_event","property":"payload.data.0.button.last_event","propertyType":"msg","rules":[{"t":"cont","v":"initial_press","vt":"str"},{"t":"cont","v":"short_release","vt":"str"},{"t":"cont","v":"repeat","vt":"str"},{"t":"cont","v":"long_release","vt":"str"}],"checkall":"true","repair":false,"outputs":4,"x":430,"y":440,"wires":[["9708f490.335c08","19dcf962.c49ee7"],["679ac041.b2df1","7433abf6.09ddf4"],["247f63db.3b6bec"],["6050183b.247748","893962e6.dfef3"]]},{"id":"a6fb44fa.0022c8","type":"rbe","z":"8bf70583.ef9238","name":"","func":"rbe","gap":"","start":"","inout":"out","septopics":true,"property":"payload","x":810,"y":380,"wires":[["2877a094.1bfd2"]]},{"id":"2877a094.1bfd2","type":"switch","z":"8bf70583.ef9238","name":"","property":"payload","propertyType":"msg","rules":[{"t":"true"}],"checkall":"true","repair":false,"outputs":1,"x":930,"y":380,"wires":[[]]},{"id":"7433abf6.09ddf4","type":"change","z":"8bf70583.ef9238","name":"false","rules":[{"t":"set","p":"payload","pt":"msg","to":"false","tot":"bool"}],"action":"","property":"","from":"","to":"","reg":false,"x":810,"y":340,"wires":[["332474df.8d7e8c"]]},{"id":"332474df.8d7e8c","type":"delay","z":"8bf70583.ef9238","name":"2s","pauseType":"delay","timeout":"2","timeoutUnits":"seconds","rate":"1","nbRateUnits":"1","rateUnits":"second","randomFirst":"1","randomLast":"5","randomUnits":"seconds","drop":false,"x":930,"y":340,"wires":[["a6fb44fa.0022c8"]]},{"id":"679ac041.b2df1","type":"change","z":"8bf70583.ef9238","name":"true","rules":[{"t":"set","p":"payload","pt":"msg","to":"true","tot":"bool"}],"action":"","property":"","from":"","to":"","reg":false,"x":810,"y":420,"wires":[["a6fb44fa.0022c8"]]},{"id":"16add84e.450c68","type":"comment","z":"8bf70583.ef9238","name":"initial_press","info":"","x":830,"y":100,"wires":[]},{"id":"aa7b7a9.a1fcb88","type":"comment","z":"8bf70583.ef9238","name":"short_release","info":"","x":830,"y":300,"wires":[]},{"id":"f89c218f.ba5","type":"comment","z":"8bf70583.ef9238","name":"long_release","info":"","x":830,"y":620,"wires":[]},{"id":"247f63db.3b6bec","type":"change","z":"8bf70583.ef9238","name":"true","rules":[{"t":"set","p":"payload","pt":"msg","to":"true","tot":"bool"}],"action":"","property":"","from":"","to":"","reg":false,"x":810,"y":540,"wires":[[]]},{"id":"a77ccfd7.e13c7","type":"comment","z":"8bf70583.ef9238","name":"repeat","info":"","x":810,"y":500,"wires":[]},{"id":"903773e6.932ce","type":"comment","z":"8bf70583.ef9238","name":"PLEASE READ - DOUBLE CLICK","info":"Output 1:\nThe **initial_press** comes ALWAYS directly after you push the Button. Quickest response possible!\n\nOutput 2:\nThe **short_release** will just appear after the **initial_press**, when you pushed the Button quick.\n\nOutput 3:\nThe **repeat** will appear if you hold the button, and will send a message every second until you release it.\n\nOutput 4:\nThe **long_release** will appear after the **repeat** ENDED!\n\n\n--------------------------------\nAll outputs are boolean **true**\n--------------------------------\n\n\nThe delays will reset the RBE node with a false.\nYou can adjust the times for your needs, but this worked for me prefectly.","x":440,"y":380,"wires":[]},{"id":"9871853c.daca88","type":"subflow","name":"HUE light / grouped_light Event Filter","info":"","category":"","in":[{"x":240,"y":320,"wires":[{"id":"723824.285ab7dc"}]}],"out":[{"x":940,"y":240,"wires":[{"id":"1d399dd5.f0d092","port":0}]},{"x":940,"y":320,"wires":[{"id":"1d399dd5.f0d092","port":0},{"id":"6f59fcc3.9545d4","port":0}]},{"x":940,"y":400,"wires":[{"id":"6f59fcc3.9545d4","port":0}]}],"env":[],"color":"#DDAA99"},{"id":"6fcf6632.eb3b78","type":"rbe","z":"9871853c.daca88","name":"","func":"rbe","gap":"","start":"","inout":"out","septopics":true,"property":"payload","x":670,"y":240,"wires":[["1d399dd5.f0d092"]]},{"id":"1d399dd5.f0d092","type":"switch","z":"9871853c.daca88","name":"","property":"payload","propertyType":"msg","rules":[{"t":"true"}],"checkall":"true","repair":false,"outputs":1,"x":790,"y":240,"wires":[[]]},{"id":"ba3a5791.deefb8","type":"change","z":"9871853c.daca88","name":"false","rules":[{"t":"set","p":"payload","pt":"msg","to":"false","tot":"bool"}],"action":"","property":"","from":"","to":"","reg":false,"x":670,"y":200,"wires":[["5be5f9fa.70da28"]]},{"id":"5be5f9fa.70da28","type":"delay","z":"9871853c.daca88","name":"2s","pauseType":"delay","timeout":"2","timeoutUnits":"seconds","rate":"1","nbRateUnits":"1","rateUnits":"second","randomFirst":"1","randomLast":"5","randomUnits":"seconds","drop":false,"x":790,"y":200,"wires":[["6fcf6632.eb3b78"]]},{"id":"92e430e6.e4f8b","type":"change","z":"9871853c.daca88","name":"True","rules":[{"t":"set","p":"payload","pt":"msg","to":"true","tot":"bool"}],"action":"","property":"","from":"","to":"","reg":false,"x":670,"y":280,"wires":[["6fcf6632.eb3b78"]]},{"id":"5283cb37.b24944","type":"delay","z":"9871853c.daca88","name":"2s","pauseType":"delay","timeout":"2","timeoutUnits":"seconds","rate":"1","nbRateUnits":"1","rateUnits":"second","randomFirst":"1","randomLast":"5","randomUnits":"seconds","drop":false,"x":790,"y":440,"wires":[["3629d7ed.666e58"]]},{"id":"3629d7ed.666e58","type":"rbe","z":"9871853c.daca88","name":"","func":"rbe","gap":"","start":"","inout":"out","septopics":true,"property":"payload","x":670,"y":400,"wires":[["6f59fcc3.9545d4"]]},{"id":"70641e2a.2bfd3","type":"change","z":"9871853c.daca88","name":"false","rules":[{"t":"set","p":"payload","pt":"msg","to":"false","tot":"bool"}],"action":"","property":"","from":"","to":"","reg":false,"x":670,"y":360,"wires":[["3629d7ed.666e58"]]},{"id":"7ebfaa72.65c164","type":"change","z":"9871853c.daca88","name":"true","rules":[{"t":"set","p":"payload","pt":"msg","to":"true","tot":"bool"}],"action":"","property":"","from":"","to":"","reg":false,"x":670,"y":440,"wires":[["5283cb37.b24944"]]},{"id":"6f59fcc3.9545d4","type":"switch","z":"9871853c.daca88","name":"","property":"payload","propertyType":"msg","rules":[{"t":"false"}],"checkall":"true","repair":false,"outputs":1,"x":790,"y":400,"wires":[[]]},{"id":"723824.285ab7dc","type":"switch","z":"9871853c.daca88","name":"payload.data.0.on.on","property":"payload.data.0.on.on","propertyType":"msg","rules":[{"t":"true"},{"t":"false"}],"checkall":"true","repair":false,"outputs":2,"x":400,"y":320,"wires":[["92e430e6.e4f8b","ba3a5791.deefb8"],["70641e2a.2bfd3","7ebfaa72.65c164"]]},{"id":"a4b25151.70038","type":"comment","z":"9871853c.daca88","name":"On","info":"","x":1030,"y":240,"wires":[]},{"id":"106e5c42.6b47d4","type":"comment","z":"9871853c.daca88","name":"On / Off","info":"","x":1030,"y":320,"wires":[]},{"id":"a4bc314c.bdd96","type":"comment","z":"9871853c.daca88","name":"Off","info":"","x":1030,"y":400,"wires":[]},{"id":"d04780f0.0c9b4","type":"comment","z":"9871853c.daca88","name":"PLEASE READ - DOUBLE CLICK","info":"Output 1:\nThis output will send a **true** when Lights or Groups are turned on.\n\nOutput 2:\nThis output will send a **true** when Lights or Groups are turned on AND a **false** when Lights or Groups are turned off.\n\nOutput 3:\nThis output will send a **false** when Lights or Groups are turned off\n\n\n\nDepending on your Situation it can be useful just to have a **true** OR **false** OR **both** states in your Flow. Thats the reason i built this Subflow.\nJust use the Output that makes you happy :)\n\n\n-----------------------\nAll outputs are boolean \n-----------------------\n\n\nThe delays will reset the RBE nodes.\nYou can adjust the times for your needs, but this worked for me prefectly.","x":360,"y":280,"wires":[]},{"id":"313c0097.f1216","type":"subflow","name":"HUE - Motion Sensor Event Filter","info":"","category":"","in":[{"x":380,"y":280,"wires":[{"id":"f00de543.b72668"}]}],"out":[{"x":960,"y":200,"wires":[{"id":"6bf15156.15b6f","port":0}]},{"x":960,"y":280,"wires":[{"id":"6bf15156.15b6f","port":0},{"id":"26f8a17a.e1b86e","port":0}]},{"x":960,"y":360,"wires":[{"id":"26f8a17a.e1b86e","port":0}]}],"env":[],"color":"#DDAA99"},{"id":"f00de543.b72668","type":"switch","z":"313c0097.f1216","name":"payload.data.0.motion.motion","property":"payload.data.0.motion.motion","propertyType":"msg","rules":[{"t":"true"},{"t":"false"}],"checkall":"true","repair":false,"outputs":2,"x":570,"y":280,"wires":[["6bf15156.15b6f"],["26f8a17a.e1b86e"]]},{"id":"6bf15156.15b6f","type":"change","z":"313c0097.f1216","name":"true","rules":[{"t":"set","p":"payload","pt":"msg","to":"true","tot":"bool"}],"action":"","property":"","from":"","to":"","reg":false,"x":830,"y":240,"wires":[[]]},{"id":"26f8a17a.e1b86e","type":"change","z":"313c0097.f1216","name":"false","rules":[{"t":"set","p":"payload","pt":"msg","to":"false","tot":"bool"}],"action":"","property":"","from":"","to":"","reg":false,"x":830,"y":320,"wires":[[]]},{"id":"94e24bce.4cf888","type":"comment","z":"313c0097.f1216","name":"PLEASE READ - DOUBLE CLICK","info":"Output 1:\nWill send just an **true** when Motion is detected\n\nOutput 2:\nWill send an **true** when Motion is detected and a **false** if no motion is detected any longer.\n\nOutput 3:\nWill send just an **false** when no Motion is detected any longer.\n\n\n-----------------------\nAll outputs are boolean\n-----------------------\n\nMost easy Subflow, but convinient when lots of sensors need to be set up.","x":580,"y":240,"wires":[]},{"id":"3c1e2a8e.9361c6","type":"comment","z":"313c0097.f1216","name":"motion true","info":"","x":1060,"y":200,"wires":[]},{"id":"dad8bfd3.3e71d","type":"comment","z":"313c0097.f1216","name":"motion false","info":"","x":1070,"y":360,"wires":[]},{"id":"ed505a4f.d8e6d8","type":"comment","z":"313c0097.f1216","name":"motion true / false","info":"","x":1090,"y":280,"wires":[]},{"id":"f741faee.58c1b8","type":"subflow:313c0097.f1216","z":"c4bb6fdc.f0e168","name":"","x":2080,"y":1100,"wires":[["6d556138.52817"],["84274d72.bb878"],["e54a3a18.8b7b48"]]},{"id":"f67c4a86.468268","type":"subflow:9871853c.daca88","z":"c4bb6fdc.f0e168","name":"","x":2070,"y":1260,"wires":[["93f6fb8a.e805d8"],["30079851.1d8dd8"],["8d03be5e.58152"]]},{"id":"542044db.e0494c","type":"subflow:8bf70583.ef9238","z":"c4bb6fdc.f0e168","name":"","env":[],"x":2110,"y":920,"wires":[["d5969d46.b7d7d"],["203ce51a.297d2a"],["a6e714a6.f34528"],["506de5ae.1c40bc"]]}]